{"as_of": "20260417", "first_date": "20251103", "codes": ["C_NTD", "LITE US", "RDI_JPY", "MU US", "C_USD", "GOOGL US", "SNDK US", "AVGO US", "NVDA US", "6787 JP", "ENR GY", "GLW US", "5801 JP", "CIEN US", "RHM GY", "3017", "6515", "300308 CH", "2330", "GEV US", "CLS US", "TER US", "2308", "5706 JP", "COHR US", "HOT GY", "5803 JP", "KTOS US", "RDI_NTD", "005930 KS", "2383", "3037", "CCJ US", "3665", "3110 JP", "BE US", "285A JP", "009150 KS", "WDC US", "RDI_USD", "6857 JP", "6590 JP", "9984 JP", "5016 JP", "5274", "7769", "CRDO US", "AMD US", "RR/ LN", "7011 JP", "COIN US", "PLTR US", "HOOD US", "4062 JP", "FORM US", "MRVL US", "CRWD US", "FSLY US", "SNOW US", "TSEM US", "2454", "AIXA GY", "2368", "2360", "7826 JP", "KLAC US", "3715", "6525 JP", "SAF FP", "268A JP", "NBIS US", "LGN US", "CWR LN", "SOI FP", "OKLO US", "AXTI US", "LEU US", "6869 HK", "4971 JP", "VIAV US", "BKSY US", "KEYS US", "SOLS US", "6997 JP", "MP US", "C_CNH", "3711", "SMHN GY", "M_USD", "RKLB US"], "prices": {"C_NTD": [], "LITE US": [], "RDI_JPY": [], "MU US": [], "C_USD": [], "GOOGL US": [], "SNDK US": [], "AVGO US": [], "NVDA US": [], "6787 JP": [], "ENR GY": [], "GLW US": [], "5801 JP": [], "CIEN US": [], "RHM GY": [], "3017": [{"date": "20251103", "close": 1495.0}, {"date": "20251104", "close": 1435.0}, {"date": "20251105", "close": 1445.0}, {"date": "20251106", "close": 1495.0}, {"date": "20251107", "close": 1465.0}, {"date": "20251110", "close": 1550.0}, {"date": "20251111", "close": 1540.0}, {"date": "20251112", "close": 1505.0}, {"date": "20251113", "close": 1495.0}, {"date": "20251114", "close": 1420.0}, {"date": "20251117", "close": 1420.0}, {"date": "20251118", "close": 1370.0}, {"date": "20251119", "close": 1340.0}, {"date": "20251120", "close": 1335.0}, {"date": "20251121", "close": 1240.0}, {"date": "20251124", "close": 1245.0}, {"date": "20251125", "close": 1315.0}, {"date": "20251126", "close": 1385.0}, {"date": "20251127", "close": 1395.0}, {"date": "20251128", "close": 1375.0}, {"date": "20251201", "close": 1340.0}, {"date": "20251202", "close": 1315.0}, {"date": "20251203", "close": 1355.0}, {"date": "20251204", "close": 1325.0}, {"date": "20251205", "close": 1385.0}, {"date": "20251208", "close": 1385.0}, {"date": "20251209", "close": 1410.0}, {"date": "20251210", "close": 1425.0}, {"date": "20251211", "close": 1430.0}, {"date": "20251212", "close": 1425.0}, {"date": "20251215", "close": 1380.0}, {"date": "20251216", "close": 1345.0}, {"date": "20251217", "close": 1340.0}, {"date": "20251218", "close": 1360.0}, {"date": "20251219", "close": 1450.0}, {"date": "20251222", "close": 1475.0}, {"date": "20251223", "close": 1510.0}, {"date": "20251224", "close": 1500.0}, {"date": "20251226", "close": 1520.0}, {"date": "20251229", "close": 1545.0}, {"date": "20251230", "close": 1530.0}, {"date": "20251231", "close": 1510.0}, {"date": "20260102", "close": 1455.0}, {"date": "20260105", "close": 1450.0}, {"date": "20260106", "close": 1425.0}, {"date": "20260107", "close": 1375.0}, {"date": "20260108", "close": 1355.0}, {"date": "20260109", "close": 1375.0}, {"date": "20260112", "close": 1355.0}, {"date": "20260113", "close": 1345.0}, {"date": "20260114", "close": 1420.0}, {"date": "20260115", "close": 1380.0}, {"date": "20260116", "close": 1360.0}, {"date": "20260119", "close": 1280.0}, {"date": "20260120", "close": 1295.0}, {"date": "20260121", "close": 1280.0}, {"date": "20260122", "close": 1355.0}, {"date": "20260123", "close": 1375.0}, {"date": "20260126", "close": 1370.0}, {"date": "20260127", "close": 1420.0}, {"date": "20260128", "close": 1465.0}, {"date": "20260129", "close": 1495.0}, {"date": "20260130", "close": 1460.0}, {"date": "20260202", "close": 1490.0}, {"date": "20260203", "close": 1635.0}, {"date": "20260204", "close": 1675.0}, {"date": "20260205", "close": 1630.0}, {"date": "20260206", "close": 1595.0}, {"date": "20260209", "close": 1600.0}, {"date": "20260210", "close": 1620.0}, {"date": "20260211", "close": 1605.0}, {"date": "20260223", "close": 1520.0}, {"date": "20260224", "close": 1550.0}, {"date": "20260225", "close": 1675.0}, {"date": "20260226", "close": 1765.0}, {"date": "20260302", "close": 1765.0}, {"date": "20260303", "close": 1795.0}, {"date": "20260304", "close": 1750.0}, {"date": "20260305", "close": 1820.0}, {"date": "20260306", "close": 1845.0}, {"date": "20260309", "close": 1665.0}, {"date": "20260310", "close": 1695.0}, {"date": "20260311", "close": 1860.0}, {"date": "20260312", "close": 1875.0}, {"date": "20260313", "close": 1865.0}, {"date": "20260316", "close": 1830.0}, {"date": "20260317", "close": 1905.0}, {"date": "20260318", "close": 1850.0}, {"date": "20260319", "close": 2015.0}, {"date": "20260320", "close": 2050.0}, {"date": "20260323", "close": 1995.0}, {"date": "20260324", "close": 1945.0}, {"date": "20260325", "close": 2100.0}, {"date": "20260326", "close": 2275.0}, {"date": "20260327", "close": 2195.0}, {"date": "20260330", "close": 2135.0}, {"date": "20260331", "close": 1990.0}, {"date": "20260401", "close": 2110.0}, {"date": "20260402", "close": 2070.0}, {"date": "20260407", "close": 2030.0}, {"date": "20260408", "close": 2230.0}, {"date": "20260409", "close": 2235.0}, {"date": "20260410", "close": 2265.0}, {"date": "20260413", "close": 2200.0}, {"date": "20260414", "close": 2310.0}, {"date": "20260415", "close": 2325.0}, {"date": "20260416", "close": 2440.0}, {"date": "20260417", "close": 2400.0}], "6515": [{"date": "20251103", "close": 2440.0}, {"date": "20251104", "close": 2420.0}, {"date": "20251105", "close": 2415.0}, {"date": "20251106", "close": 2500.0}, {"date": "20251107", "close": 2380.0}, {"date": "20251110", "close": 2360.0}, {"date": "20251111", "close": 2205.0}, {"date": "20251112", "close": 2190.0}, {"date": "20251113", "close": 2185.0}, {"date": "20251114", "close": 2195.0}, {"date": "20251117", "close": 2205.0}, {"date": "20251118", "close": 2160.0}, {"date": "20251119", "close": 2140.0}, {"date": "20251120", "close": 2350.0}, {"date": "20251121", "close": 2310.0}, {"date": "20251124", "close": 2475.0}, {"date": "20251125", "close": 2515.0}, {"date": "20251126", "close": 2645.0}, {"date": "20251127", "close": 2750.0}, {"date": "20251128", "close": 2830.0}, {"date": "20251201", "close": 2550.0}, {"date": "20251202", "close": 2560.0}, {"date": "20251203", "close": 2585.0}, {"date": "20251204", "close": 2570.0}, {"date": "20251205", "close": 2560.0}, {"date": "20251208", "close": 2520.0}, {"date": "20251209", "close": 2675.0}, {"date": "20251210", "close": 2685.0}, {"date": "20251211", "close": 2665.0}, {"date": "20251212", "close": 2800.0}, {"date": "20251215", "close": 2785.0}, {"date": "20251216", "close": 2770.0}, {"date": "20251217", "close": 2570.0}, {"date": "20251218", "close": 2560.0}, {"date": "20251219", "close": 2625.0}, {"date": "20251222", "close": 2590.0}, {"date": "20251223", "close": 2585.0}, {"date": "20251224", "close": 2635.0}, {"date": "20251226", "close": 2895.0}, {"date": "20251229", "close": 2775.0}, {"date": "20251230", "close": 2875.0}, {"date": "20251231", "close": 2840.0}, {"date": "20260102", "close": 2895.0}, {"date": "20260105", "close": 3060.0}, {"date": "20260106", "close": 3130.0}, {"date": "20260107", "close": 3305.0}, {"date": "20260108", "close": 3175.0}, {"date": "20260109", "close": 3490.0}, {"date": "20260112", "close": 3470.0}, {"date": "20260113", "close": 3450.0}, {"date": "20260114", "close": 3495.0}, {"date": "20260115", "close": 3450.0}, {"date": "20260116", "close": 3535.0}, {"date": "20260119", "close": 3460.0}, {"date": "20260120", "close": 3740.0}, {"date": "20260121", "close": 3825.0}, {"date": "20260122", "close": 3750.0}, {"date": "20260123", "close": 3905.0}, {"date": "20260126", "close": 4065.0}, {"date": "20260127", "close": 4275.0}, {"date": "20260128", "close": 4015.0}, {"date": "20260129", "close": 3900.0}, {"date": "20260130", "close": 3905.0}, {"date": "20260202", "close": 4060.0}, {"date": "20260203", "close": 4465.0}, {"date": "20260204", "close": 4555.0}, {"date": "20260205", "close": 4425.0}, {"date": "20260206", "close": 4510.0}, {"date": "20260209", "close": 4720.0}, {"date": "20260210", "close": 4895.0}, {"date": "20260211", "close": 5005.0}, {"date": "20260223", "close": 4695.0}, {"date": "20260224", "close": 4765.0}, {"date": "20260225", "close": 5000.0}, {"date": "20260226", "close": 5115.0}, {"date": "20260302", "close": 4775.0}, {"date": "20260303", "close": 4730.0}, {"date": "20260304", "close": 4525.0}, {"date": "20260305", "close": 4775.0}, {"date": "20260306", "close": 5250.0}, {"date": "20260309", "close": 4980.0}, {"date": "20260310", "close": 5475.0}, {"date": "20260311", "close": 5900.0}, {"date": "20260312", "close": 6330.0}, {"date": "20260313", "close": 6285.0}, {"date": "20260316", "close": 6160.0}, {"date": "20260317", "close": 6620.0}, {"date": "20260318", "close": 7220.0}, {"date": "20260319", "close": 7210.0}, {"date": "20260320", "close": 7930.0}, {"date": "20260323", "close": 7885.0}, {"date": "20260324", "close": 8190.0}, {"date": "20260325", "close": 8450.0}, {"date": "20260326", "close": 8145.0}, {"date": "20260327", "close": 7915.0}, {"date": "20260330", "close": 7675.0}, {"date": "20260331", "close": 7150.0}, {"date": "20260401", "close": 7290.0}, {"date": "20260402", "close": 6605.0}, {"date": "20260407", "close": 7100.0}, {"date": "20260408", "close": 7810.0}, {"date": "20260409", "close": 7995.0}, {"date": "20260410", "close": 7930.0}, {"date": "20260413", "close": 8560.0}, {"date": "20260414", "close": 8470.0}, {"date": "20260415", "close": 9065.0}, {"date": "20260416", "close": 9820.0}, {"date": "20260417", "close": 10305.0}], "300308 CH": [], "2330": [{"date": "20251103", "close": 1510.0}, {"date": "20251104", "close": 1505.0}, {"date": "20251105", "close": 1460.0}, {"date": "20251106", "close": 1465.0}, {"date": "20251107", "close": 1460.0}, {"date": "20251110", "close": 1475.0}, {"date": "20251111", "close": 1465.0}, {"date": "20251112", "close": 1475.0}, {"date": "20251113", "close": 1460.0}, {"date": "20251114", "close": 1430.0}, {"date": "20251117", "close": 1445.0}, {"date": "20251118", "close": 1405.0}, {"date": "20251119", "close": 1395.0}, {"date": "20251120", "close": 1455.0}, {"date": "20251121", "close": 1385.0}, {"date": "20251124", "close": 1375.0}, {"date": "20251125", "close": 1415.0}, {"date": "20251126", "close": 1440.0}, {"date": "20251127", "close": 1435.0}, {"date": "20251128", "close": 1440.0}, {"date": "20251201", "close": 1410.0}, {"date": "20251202", "close": 1430.0}, {"date": "20251203", "close": 1450.0}, {"date": "20251204", "close": 1445.0}, {"date": "20251205", "close": 1460.0}, {"date": "20251208", "close": 1495.0}, {"date": "20251209", "close": 1480.0}, {"date": "20251210", "close": 1505.0}, {"date": "20251211", "close": 1470.0}, {"date": "20251212", "close": 1480.0}, {"date": "20251215", "close": 1450.0}, {"date": "20251216", "close": 1435.0}, {"date": "20251217", "close": 1430.0}, {"date": "20251218", "close": 1430.0}, {"date": "20251219", "close": 1430.0}, {"date": "20251222", "close": 1465.0}, {"date": "20251223", "close": 1490.0}, {"date": "20251224", "close": 1495.0}, {"date": "20251226", "close": 1510.0}, {"date": "20251229", "close": 1530.0}, {"date": "20251230", "close": 1520.0}, {"date": "20251231", "close": 1550.0}, {"date": "20260102", "close": 1585.0}, {"date": "20260105", "close": 1670.0}, {"date": "20260106", "close": 1705.0}, {"date": "20260107", "close": 1675.0}, {"date": "20260108", "close": 1685.0}, {"date": "20260109", "close": 1680.0}, {"date": "20260112", "close": 1690.0}, {"date": "20260113", "close": 1710.0}, {"date": "20260114", "close": 1710.0}, {"date": "20260115", "close": 1690.0}, {"date": "20260116", "close": 1740.0}, {"date": "20260119", "close": 1760.0}, {"date": "20260120", "close": 1775.0}, {"date": "20260121", "close": 1740.0}, {"date": "20260122", "close": 1760.0}, {"date": "20260123", "close": 1770.0}, {"date": "20260126", "close": 1755.0}, {"date": "20260127", "close": 1780.0}, {"date": "20260128", "close": 1820.0}, {"date": "20260129", "close": 1805.0}, {"date": "20260130", "close": 1775.0}, {"date": "20260202", "close": 1765.0}, {"date": "20260203", "close": 1800.0}, {"date": "20260204", "close": 1785.0}, {"date": "20260205", "close": 1765.0}, {"date": "20260206", "close": 1780.0}, {"date": "20260209", "close": 1815.0}, {"date": "20260210", "close": 1880.0}, {"date": "20260211", "close": 1915.0}, {"date": "20260223", "close": 1900.0}, {"date": "20260224", "close": 1965.0}, {"date": "20260225", "close": 2015.0}, {"date": "20260226", "close": 1995.0}, {"date": "20260302", "close": 1975.0}, {"date": "20260303", "close": 1935.0}, {"date": "20260304", "close": 1865.0}, {"date": "20260305", "close": 1900.0}, {"date": "20260306", "close": 1890.0}, {"date": "20260309", "close": 1810.0}, {"date": "20260310", "close": 1850.0}, {"date": "20260311", "close": 1940.0}, {"date": "20260312", "close": 1885.0}, {"date": "20260313", "close": 1865.0}, {"date": "20260316", "close": 1845.0}, {"date": "20260317", "close": 1870.0}, {"date": "20260318", "close": 1905.0}, {"date": "20260319", "close": 1850.0}, {"date": "20260320", "close": 1840.0}, {"date": "20260323", "close": 1810.0}, {"date": "20260324", "close": 1810.0}, {"date": "20260325", "close": 1845.0}, {"date": "20260326", "close": 1840.0}, {"date": "20260327", "close": 1820.0}, {"date": "20260330", "close": 1780.0}, {"date": "20260331", "close": 1760.0}, {"date": "20260401", "close": 1855.0}, {"date": "20260402", "close": 1810.0}, {"date": "20260407", "close": 1860.0}, {"date": "20260408", "close": 1950.0}, {"date": "20260409", "close": 1955.0}, {"date": "20260410", "close": 2000.0}, {"date": "20260413", "close": 1990.0}, {"date": "20260414", "close": 2055.0}, {"date": "20260415", "close": 2080.0}, {"date": "20260416", "close": 2085.0}, {"date": "20260417", "close": 2030.0}], "GEV US": [], "CLS US": [], "TER US": [], "2308": [{"date": "20251103", "close": 983.0}, {"date": "20251104", "close": 975.0}, {"date": "20251105", "close": 967.0}, {"date": "20251106", "close": 978.0}, {"date": "20251107", "close": 965.0}, {"date": "20251110", "close": 982.0}, {"date": "20251111", "close": 972.0}, {"date": "20251112", "close": 967.0}, {"date": "20251113", "close": 958.0}, {"date": "20251114", "close": 922.0}, {"date": "20251117", "close": 916.0}, {"date": "20251118", "close": 898.0}, {"date": "20251119", "close": 894.0}, {"date": "20251120", "close": 954.0}, {"date": "20251121", "close": 895.0}, {"date": "20251124", "close": 893.0}, {"date": "20251125", "close": 910.0}, {"date": "20251126", "close": 945.0}, {"date": "20251127", "close": 942.0}, {"date": "20251128", "close": 932.0}, {"date": "20251201", "close": 973.0}, {"date": "20251202", "close": 989.0}, {"date": "20251203", "close": 997.0}, {"date": "20251204", "close": 999.0}, {"date": "20251205", "close": 979.0}, {"date": "20251208", "close": 979.0}, {"date": "20251209", "close": 971.0}, {"date": "20251210", "close": 968.0}, {"date": "20251211", "close": 945.0}, {"date": "20251212", "close": 938.0}, {"date": "20251215", "close": 922.0}, {"date": "20251216", "close": 901.0}, {"date": "20251217", "close": 890.0}, {"date": "20251218", "close": 891.0}, {"date": "20251219", "close": 911.0}, {"date": "20251222", "close": 953.0}, {"date": "20251223", "close": 943.0}, {"date": "20251224", "close": 955.0}, {"date": "20251226", "close": 956.0}, {"date": "20251229", "close": 962.0}, {"date": "20251230", "close": 961.0}, {"date": "20251231", "close": 963.0}, {"date": "20260102", "close": 995.0}, {"date": "20260105", "close": 1010.0}, {"date": "20260106", "close": 1050.0}, {"date": "20260107", "close": 1030.0}, {"date": "20260108", "close": 1010.0}, {"date": "20260109", "close": 1015.0}, {"date": "20260112", "close": 1055.0}, {"date": "20260113", "close": 1030.0}, {"date": "20260114", "close": 1060.0}, {"date": "20260115", "close": 1045.0}, {"date": "20260116", "close": 1125.0}, {"date": "20260119", "close": 1120.0}, {"date": "20260120", "close": 1130.0}, {"date": "20260121", "close": 1135.0}, {"date": "20260122", "close": 1245.0}, {"date": "20260123", "close": 1260.0}, {"date": "20260126", "close": 1230.0}, {"date": "20260127", "close": 1250.0}, {"date": "20260128", "close": 1280.0}, {"date": "20260129", "close": 1255.0}, {"date": "20260130", "close": 1220.0}, {"date": "20260202", "close": 1175.0}, {"date": "20260203", "close": 1215.0}, {"date": "20260204", "close": 1210.0}, {"date": "20260205", "close": 1150.0}, {"date": "20260206", "close": 1160.0}, {"date": "20260209", "close": 1180.0}, {"date": "20260210", "close": 1185.0}, {"date": "20260211", "close": 1260.0}, {"date": "20260223", "close": 1305.0}, {"date": "20260224", "close": 1385.0}, {"date": "20260225", "close": 1435.0}, {"date": "20260226", "close": 1430.0}, {"date": "20260302", "close": 1425.0}, {"date": "20260303", "close": 1340.0}, {"date": "20260304", "close": 1255.0}, {"date": "20260305", "close": 1335.0}, {"date": "20260306", "close": 1320.0}, {"date": "20260309", "close": 1220.0}, {"date": "20260310", "close": 1290.0}, {"date": "20260311", "close": 1400.0}, {"date": "20260312", "close": 1370.0}, {"date": "20260313", "close": 1385.0}, {"date": "20260316", "close": 1360.0}, {"date": "20260317", "close": 1440.0}, {"date": "20260318", "close": 1465.0}, {"date": "20260319", "close": 1455.0}, {"date": "20260320", "close": 1475.0}, {"date": "20260323", "close": 1410.0}, {"date": "20260324", "close": 1415.0}, {"date": "20260325", "close": 1550.0}, {"date": "20260326", "close": 1515.0}, {"date": "20260327", "close": 1510.0}, {"date": "20260330", "close": 1485.0}, {"date": "20260331", "close": 1380.0}, {"date": "20260401", "close": 1475.0}, {"date": "20260402", "close": 1430.0}, {"date": "20260407", "close": 1515.0}, {"date": "20260408", "close": 1665.0}, {"date": "20260409", "close": 1645.0}, {"date": "20260410", "close": 1735.0}, {"date": "20260413", "close": 1740.0}, {"date": "20260414", "close": 1750.0}, {"date": "20260415", "close": 1785.0}, {"date": "20260416", "close": 1845.0}, {"date": "20260417", "close": 1840.0}], "5706 JP": [], "COHR US": [], "HOT GY": [], "5803 JP": [], "KTOS US": [], "RDI_NTD": [], "005930 KS": [], "2383": [{"date": "20251103", "close": 1410.0}, {"date": "20251104", "close": 1470.0}, {"date": "20251105", "close": 1440.0}, {"date": "20251106", "close": 1450.0}, {"date": "20251107", "close": 1370.0}, {"date": "20251110", "close": 1360.0}, {"date": "20251111", "close": 1320.0}, {"date": "20251112", "close": 1345.0}, {"date": "20251113", "close": 1375.0}, {"date": "20251114", "close": 1380.0}, {"date": "20251117", "close": 1450.0}, {"date": "20251118", "close": 1350.0}, {"date": "20251119", "close": 1330.0}, {"date": "20251120", "close": 1430.0}, {"date": "20251121", "close": 1310.0}, {"date": "20251124", "close": 1320.0}, {"date": "20251125", "close": 1450.0}, {"date": "20251126", "close": 1470.0}, {"date": "20251127", "close": 1495.0}, {"date": "20251128", "close": 1525.0}, {"date": "20251201", "close": 1475.0}, {"date": "20251202", "close": 1440.0}, {"date": "20251203", "close": 1430.0}, {"date": "20251204", "close": 1425.0}, {"date": "20251205", "close": 1495.0}, {"date": "20251208", "close": 1485.0}, {"date": "20251209", "close": 1500.0}, {"date": "20251210", "close": 1600.0}, {"date": "20251211", "close": 1595.0}, {"date": "20251212", "close": 1605.0}, {"date": "20251215", "close": 1605.0}, {"date": "20251216", "close": 1495.0}, {"date": "20251217", "close": 1495.0}, {"date": "20251218", "close": 1500.0}, {"date": "20251219", "close": 1550.0}, {"date": "20251222", "close": 1600.0}, {"date": "20251223", "close": 1615.0}, {"date": "20251224", "close": 1690.0}, {"date": "20251226", "close": 1640.0}, {"date": "20251229", "close": 1675.0}, {"date": "20251230", "close": 1645.0}, {"date": "20251231", "close": 1645.0}, {"date": "20260102", "close": 1590.0}, {"date": "20260105", "close": 1620.0}, {"date": "20260106", "close": 1695.0}, {"date": "20260107", "close": 1580.0}, {"date": "20260108", "close": 1545.0}, {"date": "20260109", "close": 1565.0}, {"date": "20260112", "close": 1610.0}, {"date": "20260113", "close": 1635.0}, {"date": "20260114", "close": 1670.0}, {"date": "20260115", "close": 1570.0}, {"date": "20260116", "close": 1625.0}, {"date": "20260119", "close": 1580.0}, {"date": "20260120", "close": 1615.0}, {"date": "20260121", "close": 1560.0}, {"date": "20260122", "close": 1660.0}, {"date": "20260123", "close": 1800.0}, {"date": "20260126", "close": 1740.0}, {"date": "20260127", "close": 1820.0}, {"date": "20260128", "close": 1900.0}, {"date": "20260129", "close": 1790.0}, {"date": "20260130", "close": 1745.0}, {"date": "20260202", "close": 1785.0}, {"date": "20260203", "close": 1855.0}, {"date": "20260204", "close": 2040.0}, {"date": "20260205", "close": 1950.0}, {"date": "20260206", "close": 1925.0}, {"date": "20260209", "close": 2080.0}, {"date": "20260210", "close": 2105.0}, {"date": "20260211", "close": 2195.0}, {"date": "20260223", "close": 2175.0}, {"date": "20260224", "close": 2310.0}, {"date": "20260225", "close": 2420.0}, {"date": "20260226", "close": 2440.0}, {"date": "20260302", "close": 2380.0}, {"date": "20260303", "close": 2320.0}, {"date": "20260304", "close": 2190.0}, {"date": "20260305", "close": 2365.0}, {"date": "20260306", "close": 2360.0}, {"date": "20260309", "close": 2175.0}, {"date": "20260310", "close": 2375.0}, {"date": "20260311", "close": 2450.0}, {"date": "20260312", "close": 2600.0}, {"date": "20260313", "close": 2705.0}, {"date": "20260316", "close": 2585.0}, {"date": "20260317", "close": 2700.0}, {"date": "20260318", "close": 2700.0}, {"date": "20260319", "close": 2890.0}, {"date": "20260320", "close": 2810.0}, {"date": "20260323", "close": 2795.0}, {"date": "20260324", "close": 2685.0}, {"date": "20260325", "close": 2845.0}, {"date": "20260326", "close": 2945.0}, {"date": "20260327", "close": 2910.0}, {"date": "20260330", "close": 2785.0}, {"date": "20260331", "close": 2600.0}, {"date": "20260401", "close": 2860.0}, {"date": "20260402", "close": 2785.0}, {"date": "20260407", "close": 2885.0}, {"date": "20260408", "close": 3170.0}, {"date": "20260409", "close": 3220.0}, {"date": "20260410", "close": 3420.0}, {"date": "20260413", "close": 3325.0}, {"date": "20260414", "close": 3605.0}, {"date": "20260415", "close": 3810.0}, {"date": "20260416", "close": 3835.0}, {"date": "20260417", "close": 3800.0}], "3037": [{"date": "20251103", "close": 178.5}, {"date": "20251104", "close": 168.5}, {"date": "20251105", "close": 164.0}, {"date": "20251106", "close": 165.5}, {"date": "20251107", "close": 161.5}, {"date": "20251110", "close": 164.5}, {"date": "20251111", "close": 166.5}, {"date": "20251112", "close": 167.5}, {"date": "20251113", "close": 178.5}, {"date": "20251114", "close": 171.5}, {"date": "20251117", "close": 167.5}, {"date": "20251118", "close": 170.0}, {"date": "20251119", "close": 160.5}, {"date": "20251120", "close": 171.5}, {"date": "20251121", "close": 160.0}, {"date": "20251124", "close": 164.0}, {"date": "20251125", "close": 176.0}, {"date": "20251126", "close": 178.5}, {"date": "20251127", "close": 187.0}, {"date": "20251128", "close": 186.5}, {"date": "20251201", "close": 197.0}, {"date": "20251202", "close": 196.0}, {"date": "20251203", "close": 196.5}, {"date": "20251204", "close": 198.5}, {"date": "20251205", "close": 215.0}, {"date": "20251208", "close": 220.5}, {"date": "20251209", "close": 226.0}, {"date": "20251210", "close": 227.5}, {"date": "20251211", "close": 225.0}, {"date": "20251212", "close": 225.0}, {"date": "20251215", "close": 221.5}, {"date": "20251216", "close": 214.0}, {"date": "20251217", "close": 212.0}, {"date": "20251218", "close": 207.0}, {"date": "20251219", "close": 215.0}, {"date": "20251222", "close": 220.5}, {"date": "20251223", "close": 215.5}, {"date": "20251224", "close": 217.0}, {"date": "20251226", "close": 220.5}, {"date": "20251229", "close": 220.5}, {"date": "20251230", "close": 219.5}, {"date": "20251231", "close": 220.0}, {"date": "20260102", "close": 219.0}, {"date": "20260105", "close": 230.0}, {"date": "20260106", "close": 230.5}, {"date": "20260107", "close": 226.0}, {"date": "20260108", "close": 227.5}, {"date": "20260109", "close": 225.5}, {"date": "20260112", "close": 243.5}, {"date": "20260113", "close": 254.0}, {"date": "20260114", "close": 250.0}, {"date": "20260115", "close": 249.5}, {"date": "20260116", "close": 274.0}, {"date": "20260119", "close": 301.0}, {"date": "20260120", "close": 308.0}, {"date": "20260121", "close": 321.0}, {"date": "20260122", "close": 327.0}, {"date": "20260123", "close": 339.0}, {"date": "20260126", "close": 333.0}, {"date": "20260127", "close": 354.0}, {"date": "20260128", "close": 367.5}, {"date": "20260129", "close": 344.5}, {"date": "20260130", "close": 378.5}, {"date": "20260202", "close": 365.0}, {"date": "20260203", "close": 385.0}, {"date": "20260204", "close": 388.0}, {"date": "20260205", "close": 365.5}, {"date": "20260206", "close": 340.0}, {"date": "20260209", "close": 347.5}, {"date": "20260210", "close": 371.5}, {"date": "20260211", "close": 369.0}, {"date": "20260223", "close": 405.5}, {"date": "20260224", "close": 446.0}, {"date": "20260225", "close": 458.5}, {"date": "20260226", "close": 481.5}, {"date": "20260302", "close": 481.0}, {"date": "20260303", "close": 463.0}, {"date": "20260304", "close": 417.0}, {"date": "20260305", "close": 450.0}, {"date": "20260306", "close": 432.0}, {"date": "20260309", "close": 389.0}, {"date": "20260310", "close": 424.0}, {"date": "20260311", "close": 466.0}, {"date": "20260312", "close": 480.0}, {"date": "20260313", "close": 508.0}, {"date": "20260316", "close": 549.0}, {"date": "20260317", "close": 543.0}, {"date": "20260318", "close": 580.0}, {"date": "20260319", "close": 581.0}, {"date": "20260320", "close": 554.0}, {"date": "20260323", "close": 499.0}, {"date": "20260324", "close": 460.0}, {"date": "20260325", "close": 506.0}, {"date": "20260326", "close": 502.0}, {"date": "20260327", "close": 505.0}, {"date": "20260330", "close": 493.5}, {"date": "20260331", "close": 444.5}, {"date": "20260401", "close": 488.5}, {"date": "20260402", "close": 519.0}, {"date": "20260407", "close": 564.0}, {"date": "20260408", "close": 620.0}, {"date": "20260409", "close": 625.0}, {"date": "20260410", "close": 638.0}, {"date": "20260413", "close": 626.0}, {"date": "20260414", "close": 597.0}, {"date": "20260415", "close": 618.0}, {"date": "20260416", "close": 645.0}, {"date": "20260417", "close": 643.0}], "CCJ US": [], "3665": [{"date": "20251103", "close": 1455.0}, {"date": "20251104", "close": 1380.0}, {"date": "20251105", "close": 1375.0}, {"date": "20251106", "close": 1370.0}, {"date": "20251107", "close": 1415.0}, {"date": "20251110", "close": 1535.0}, {"date": "20251111", "close": 1550.0}, {"date": "20251112", "close": 1500.0}, {"date": "20251113", "close": 1605.0}, {"date": "20251114", "close": 1520.0}, {"date": "20251117", "close": 1625.0}, {"date": "20251118", "close": 1570.0}, {"date": "20251119", "close": 1580.0}, {"date": "20251120", "close": 1680.0}, {"date": "20251121", "close": 1605.0}, {"date": "20251124", "close": 1560.0}, {"date": "20251125", "close": 1545.0}, {"date": "20251126", "close": 1500.0}, {"date": "20251127", "close": 1540.0}, {"date": "20251128", "close": 1610.0}, {"date": "20251201", "close": 1600.0}, {"date": "20251202", "close": 1535.0}, {"date": "20251203", "close": 1525.0}, {"date": "20251204", "close": 1530.0}, {"date": "20251205", "close": 1525.0}, {"date": "20251208", "close": 1515.0}, {"date": "20251209", "close": 1470.0}, {"date": "20251210", "close": 1525.0}, {"date": "20251211", "close": 1535.0}, {"date": "20251212", "close": 1535.0}, {"date": "20251215", "close": 1475.0}, {"date": "20251216", "close": 1440.0}, {"date": "20251217", "close": 1435.0}, {"date": "20251218", "close": 1440.0}, {"date": "20251219", "close": 1440.0}, {"date": "20251222", "close": 1475.0}, {"date": "20251223", "close": 1460.0}, {"date": "20251224", "close": 1550.0}, {"date": "20251226", "close": 1545.0}, {"date": "20251229", "close": 1505.0}, {"date": "20251230", "close": 1505.0}, {"date": "20251231", "close": 1520.0}, {"date": "20260102", "close": 1525.0}, {"date": "20260105", "close": 1575.0}, {"date": "20260106", "close": 1575.0}, {"date": "20260107", "close": 1430.0}, {"date": "20260108", "close": 1410.0}, {"date": "20260109", "close": 1425.0}, {"date": "20260112", "close": 1395.0}, {"date": "20260113", "close": 1420.0}, {"date": "20260114", "close": 1495.0}, {"date": "20260115", "close": 1470.0}, {"date": "20260116", "close": 1400.0}, {"date": "20260119", "close": 1315.0}, {"date": "20260120", "close": 1340.0}, {"date": "20260121", "close": 1300.0}, {"date": "20260122", "close": 1420.0}, {"date": "20260123", "close": 1390.0}, {"date": "20260126", "close": 1430.0}, {"date": "20260127", "close": 1420.0}, {"date": "20260128", "close": 1440.0}, {"date": "20260129", "close": 1365.0}, {"date": "20260130", "close": 1300.0}, {"date": "20260202", "close": 1325.0}, {"date": "20260203", "close": 1410.0}, {"date": "20260204", "close": 1340.0}, {"date": "20260205", "close": 1260.0}, {"date": "20260206", "close": 1285.0}, {"date": "20260209", "close": 1255.0}, {"date": "20260210", "close": 1380.0}, {"date": "20260211", "close": 1365.0}, {"date": "20260223", "close": 1290.0}, {"date": "20260224", "close": 1295.0}, {"date": "20260225", "close": 1345.0}, {"date": "20260226", "close": 1410.0}, {"date": "20260302", "close": 1505.0}, {"date": "20260303", "close": 1645.0}, {"date": "20260304", "close": 1610.0}, {"date": "20260305", "close": 1725.0}, {"date": "20260306", "close": 1770.0}, {"date": "20260309", "close": 1595.0}, {"date": "20260310", "close": 1565.0}, {"date": "20260311", "close": 1655.0}, {"date": "20260312", "close": 1635.0}, {"date": "20260313", "close": 1590.0}, {"date": "20260316", "close": 1645.0}, {"date": "20260317", "close": 1740.0}, {"date": "20260318", "close": 1690.0}, {"date": "20260319", "close": 1720.0}, {"date": "20260320", "close": 1825.0}, {"date": "20260323", "close": 1770.0}, {"date": "20260324", "close": 1730.0}, {"date": "20260325", "close": 1805.0}, {"date": "20260326", "close": 1815.0}, {"date": "20260327", "close": 1860.0}, {"date": "20260330", "close": 1880.0}, {"date": "20260331", "close": 1740.0}, {"date": "20260401", "close": 1910.0}, {"date": "20260402", "close": 1915.0}, {"date": "20260407", "close": 1990.0}, {"date": "20260408", "close": 2015.0}, {"date": "20260409", "close": 2130.0}, {"date": "20260410", "close": 2200.0}, {"date": "20260413", "close": 2225.0}, {"date": "20260414", "close": 2295.0}, {"date": "20260415", "close": 2350.0}, {"date": "20260416", "close": 2395.0}, {"date": "20260417", "close": 2365.0}], "3110 JP": [], "BE US": [], "285A JP": [], "009150 KS": [], "WDC US": [], "RDI_USD": [], "6857 JP": [], "6590 JP": [], "9984 JP": [], "5016 JP": [], "5274": [{"date": "20251103", "close": 5470.0}, {"date": "20251104", "close": 5500.0}, {"date": "20251105", "close": 5285.0}, {"date": "20251106", "close": 5810.0}, {"date": "20251107", "close": 5685.0}, {"date": "20251110", "close": 5640.0}, {"date": "20251111", "close": 5625.0}, {"date": "20251112", "close": 5760.0}, {"date": "20251113", "close": 6335.0}, {"date": "20251114", "close": 5965.0}, {"date": "20251117", "close": 6120.0}, {"date": "20251118", "close": 6500.0}, {"date": "20251119", "close": 6215.0}, {"date": "20251120", "close": 6355.0}, {"date": "20251121", "close": 6075.0}, {"date": "20251124", "close": 6405.0}, {"date": "20251125", "close": 6330.0}, {"date": "20251126", "close": 6620.0}, {"date": "20251127", "close": 6650.0}, {"date": "20251128", "close": 7315.0}, {"date": "20251201", "close": 6915.0}, {"date": "20251202", "close": 6600.0}, {"date": "20251203", "close": 6565.0}, {"date": "20251204", "close": 6440.0}, {"date": "20251205", "close": 6570.0}, {"date": "20251208", "close": 6515.0}, {"date": "20251209", "close": 6690.0}, {"date": "20251210", "close": 6710.0}, {"date": "20251211", "close": 6800.0}, {"date": "20251212", "close": 6725.0}, {"date": "20251215", "close": 6795.0}, {"date": "20251216", "close": 6650.0}, {"date": "20251217", "close": 6500.0}, {"date": "20251218", "close": 6615.0}, {"date": "20251219", "close": 6580.0}, {"date": "20251222", "close": 6800.0}, {"date": "20251223", "close": 6870.0}, {"date": "20251224", "close": 6850.0}, {"date": "20251226", "close": 6930.0}, {"date": "20251229", "close": 7100.0}, {"date": "20251230", "close": 7550.0}, {"date": "20251231", "close": 7260.0}, {"date": "20260102", "close": 7255.0}, {"date": "20260105", "close": 7105.0}, {"date": "20260106", "close": 7200.0}, {"date": "20260107", "close": 7380.0}, {"date": "20260108", "close": 7650.0}, {"date": "20260109", "close": 7665.0}, {"date": "20260112", "close": 8055.0}, {"date": "20260113", "close": 8005.0}, {"date": "20260114", "close": 8085.0}, {"date": "20260115", "close": 8755.0}, {"date": "20260116", "close": 8700.0}, {"date": "20260119", "close": 8775.0}, {"date": "20260120", "close": 8635.0}, {"date": "20260121", "close": 8330.0}, {"date": "20260122", "close": 8700.0}, {"date": "20260123", "close": 8870.0}, {"date": "20260126", "close": 8880.0}, {"date": "20260127", "close": 8760.0}, {"date": "20260128", "close": 8840.0}, {"date": "20260129", "close": 9315.0}, {"date": "20260130", "close": 8880.0}, {"date": "20260202", "close": 9040.0}, {"date": "20260203", "close": 9790.0}, {"date": "20260204", "close": 9640.0}, {"date": "20260205", "close": 9130.0}, {"date": "20260206", "close": 8900.0}, {"date": "20260209", "close": 9500.0}, {"date": "20260210", "close": 9325.0}, {"date": "20260211", "close": 9725.0}, {"date": "20260223", "close": 9755.0}, {"date": "20260224", "close": 9755.0}, {"date": "20260225", "close": 9715.0}, {"date": "20260226", "close": 9730.0}, {"date": "20260302", "close": 9500.0}, {"date": "20260303", "close": 9255.0}, {"date": "20260304", "close": 8655.0}, {"date": "20260305", "close": 9520.0}, {"date": "20260306", "close": 9705.0}, {"date": "20260309", "close": 9250.0}, {"date": "20260310", "close": 9430.0}, {"date": "20260311", "close": 10055.0}, {"date": "20260312", "close": 10495.0}, {"date": "20260313", "close": 10495.0}, {"date": "20260316", "close": 10295.0}, {"date": "20260317", "close": 11320.0}, {"date": "20260318", "close": 12345.0}, {"date": "20260319", "close": 12050.0}, {"date": "20260320", "close": 11750.0}, {"date": "20260323", "close": 11465.0}, {"date": "20260324", "close": 10910.0}, {"date": "20260325", "close": 11500.0}, {"date": "20260326", "close": 11550.0}, {"date": "20260327", "close": 11555.0}, {"date": "20260330", "close": 11220.0}, {"date": "20260331", "close": 10700.0}, {"date": "20260401", "close": 11315.0}, {"date": "20260402", "close": 11690.0}, {"date": "20260407", "close": 11470.0}, {"date": "20260408", "close": 12615.0}, {"date": "20260409", "close": 12565.0}, {"date": "20260410", "close": 12580.0}, {"date": "20260413", "close": 12180.0}, {"date": "20260414", "close": 13005.0}, {"date": "20260415", "close": 13875.0}, {"date": "20260416", "close": 14480.0}, {"date": "20260417", "close": 13805.0}], "7769": [{"date": "20251103", "close": 2510.0}, {"date": "20251104", "close": 2395.0}, {"date": "20251105", "close": 2475.0}, {"date": "20251106", "close": 2415.0}, {"date": "20251107", "close": 2470.0}, {"date": "20251110", "close": 2415.0}, {"date": "20251111", "close": 2315.0}, {"date": "20251112", "close": 2295.0}, {"date": "20251113", "close": 2380.0}, {"date": "20251114", "close": 2250.0}, {"date": "20251117", "close": 2250.0}, {"date": "20251118", "close": 2385.0}, {"date": "20251119", "close": 2470.0}, {"date": "20251120", "close": 2615.0}, {"date": "20251121", "close": 2475.0}, {"date": "20251124", "close": 2600.0}, {"date": "20251125", "close": 2745.0}, {"date": "20251126", "close": 2615.0}, {"date": "20251127", "close": 2940.0}, {"date": "20251128", "close": 3000.0}, {"date": "20251201", "close": 2890.0}, {"date": "20251202", "close": 2890.0}, {"date": "20251203", "close": 3080.0}, {"date": "20251204", "close": 3045.0}, {"date": "20251205", "close": 2960.0}, {"date": "20251208", "close": 2965.0}, {"date": "20251209", "close": 2975.0}, {"date": "20251210", "close": 3145.0}, {"date": "20251211", "close": 3145.0}, {"date": "20251212", "close": 3195.0}, {"date": "20251215", "close": 3195.0}, {"date": "20251216", "close": 3190.0}, {"date": "20251217", "close": 3270.0}, {"date": "20251218", "close": 3300.0}, {"date": "20251219", "close": 3295.0}, {"date": "20251222", "close": 3300.0}, {"date": "20251223", "close": 3290.0}, {"date": "20251224", "close": 3270.0}, {"date": "20251226", "close": 3390.0}, {"date": "20251229", "close": 3380.0}, {"date": "20251230", "close": 3430.0}, {"date": "20251231", "close": 3425.0}, {"date": "20260102", "close": 3430.0}, {"date": "20260105", "close": 3340.0}, {"date": "20260106", "close": 3260.0}, {"date": "20260107", "close": 3320.0}, {"date": "20260108", "close": 3130.0}, {"date": "20260109", "close": 3295.0}, {"date": "20260112", "close": 3445.0}, {"date": "20260113", "close": 3460.0}, {"date": "20260114", "close": 3505.0}, {"date": "20260115", "close": 3465.0}, {"date": "20260116", "close": 3530.0}, {"date": "20260119", "close": 3500.0}, {"date": "20260120", "close": 3495.0}, {"date": "20260121", "close": 3575.0}, {"date": "20260122", "close": 3700.0}, {"date": "20260123", "close": 3730.0}, {"date": "20260126", "close": 3795.0}, {"date": "20260127", "close": 3775.0}, {"date": "20260128", "close": 3790.0}, {"date": "20260129", "close": 3750.0}, {"date": "20260130", "close": 3750.0}, {"date": "20260202", "close": 3750.0}, {"date": "20260203", "close": 3855.0}, {"date": "20260204", "close": 3805.0}, {"date": "20260205", "close": 3705.0}, {"date": "20260206", "close": 3690.0}, {"date": "20260209", "close": 3850.0}, {"date": "20260210", "close": 4000.0}, {"date": "20260211", "close": 4345.0}, {"date": "20260223", "close": 4400.0}, {"date": "20260224", "close": 4605.0}, {"date": "20260225", "close": 4815.0}, {"date": "20260226", "close": 4860.0}, {"date": "20260302", "close": 4375.0}, {"date": "20260303", "close": 4150.0}, {"date": "20260304", "close": 3980.0}, {"date": "20260305", "close": 4245.0}, {"date": "20260306", "close": 4215.0}, {"date": "20260309", "close": 3930.0}, {"date": "20260310", "close": 4105.0}, {"date": "20260311", "close": 4325.0}, {"date": "20260312", "close": 4325.0}, {"date": "20260313", "close": 3950.0}, {"date": "20260316", "close": 4075.0}, {"date": "20260317", "close": 4230.0}, {"date": "20260318", "close": 4380.0}, {"date": "20260319", "close": 4160.0}, {"date": "20260320", "close": 4105.0}, {"date": "20260323", "close": 3950.0}, {"date": "20260324", "close": 3720.0}, {"date": "20260325", "close": 3865.0}, {"date": "20260326", "close": 3850.0}, {"date": "20260327", "close": 3790.0}, {"date": "20260330", "close": 3710.0}, {"date": "20260331", "close": 3505.0}, {"date": "20260401", "close": 3855.0}, {"date": "20260402", "close": 3835.0}, {"date": "20260407", "close": 4010.0}, {"date": "20260408", "close": 4260.0}, {"date": "20260409", "close": 4245.0}, {"date": "20260410", "close": 4200.0}, {"date": "20260413", "close": 4100.0}, {"date": "20260414", "close": 4185.0}, {"date": "20260415", "close": 4260.0}, {"date": "20260416", "close": 4295.0}, {"date": "20260417", "close": 4500.0}], "CRDO US": [], "AMD US": [], "RR/ LN": [], "7011 JP": [], "COIN US": [], "PLTR US": [], "HOOD US": [], "4062 JP": [], "FORM US": [], "MRVL US": [], "CRWD US": [], "FSLY US": [], "SNOW US": [], "TSEM US": [], "2454": [{"date": "20251103", "close": 1300.0}, {"date": "20251104", "close": 1315.0}, {"date": "20251105", "close": 1330.0}, {"date": "20251106", "close": 1290.0}, {"date": "20251107", "close": 1260.0}, {"date": "20251110", "close": 1250.0}, {"date": "20251111", "close": 1240.0}, {"date": "20251112", "close": 1245.0}, {"date": "20251113", "close": 1245.0}, {"date": "20251114", "close": 1230.0}, {"date": "20251117", "close": 1230.0}, {"date": "20251118", "close": 1170.0}, {"date": "20251119", "close": 1160.0}, {"date": "20251120", "close": 1185.0}, {"date": "20251121", "close": 1145.0}, {"date": "20251124", "close": 1150.0}, {"date": "20251125", "close": 1185.0}, {"date": "20251126", "close": 1300.0}, {"date": "20251127", "close": 1340.0}, {"date": "20251128", "close": 1395.0}, {"date": "20251201", "close": 1445.0}, {"date": "20251202", "close": 1415.0}, {"date": "20251203", "close": 1400.0}, {"date": "20251204", "close": 1405.0}, {"date": "20251205", "close": 1425.0}, {"date": "20251208", "close": 1440.0}, {"date": "20251209", "close": 1420.0}, {"date": "20251210", "close": 1460.0}, {"date": "20251211", "close": 1395.0}, {"date": "20251212", "close": 1405.0}, {"date": "20251215", "close": 1420.0}, {"date": "20251216", "close": 1420.0}, {"date": "20251217", "close": 1425.0}, {"date": "20251218", "close": 1420.0}, {"date": "20251219", "close": 1410.0}, {"date": "20251222", "close": 1400.0}, {"date": "20251223", "close": 1390.0}, {"date": "20251224", "close": 1380.0}, {"date": "20251226", "close": 1385.0}, {"date": "20251229", "close": 1420.0}, {"date": "20251230", "close": 1420.0}, {"date": "20251231", "close": 1430.0}, {"date": "20260102", "close": 1470.0}, {"date": "20260105", "close": 1525.0}, {"date": "20260106", "close": 1485.0}, {"date": "20260107", "close": 1490.0}, {"date": "20260108", "close": 1445.0}, {"date": "20260109", "close": 1420.0}, {"date": "20260112", "close": 1445.0}, {"date": "20260113", "close": 1485.0}, {"date": "20260114", "close": 1500.0}, {"date": "20260115", "close": 1490.0}, {"date": "20260116", "close": 1505.0}, {"date": "20260119", "close": 1485.0}, {"date": "20260120", "close": 1485.0}, {"date": "20260121", "close": 1465.0}, {"date": "20260122", "close": 1485.0}, {"date": "20260123", "close": 1630.0}, {"date": "20260126", "close": 1770.0}, {"date": "20260127", "close": 1775.0}, {"date": "20260128", "close": 1780.0}, {"date": "20260129", "close": 1780.0}, {"date": "20260130", "close": 1760.0}, {"date": "20260202", "close": 1705.0}, {"date": "20260203", "close": 1795.0}, {"date": "20260204", "close": 1800.0}, {"date": "20260205", "close": 1770.0}, {"date": "20260206", "close": 1710.0}, {"date": "20260209", "close": 1830.0}, {"date": "20260210", "close": 1845.0}, {"date": "20260211", "close": 1855.0}, {"date": "20260223", "close": 1795.0}, {"date": "20260224", "close": 1825.0}, {"date": "20260225", "close": 1870.0}, {"date": "20260226", "close": 1945.0}, {"date": "20260302", "close": 1900.0}, {"date": "20260303", "close": 1815.0}, {"date": "20260304", "close": 1720.0}, {"date": "20260305", "close": 1775.0}, {"date": "20260306", "close": 1765.0}, {"date": "20260309", "close": 1665.0}, {"date": "20260310", "close": 1705.0}, {"date": "20260311", "close": 1765.0}, {"date": "20260312", "close": 1785.0}, {"date": "20260313", "close": 1720.0}, {"date": "20260316", "close": 1710.0}, {"date": "20260317", "close": 1730.0}, {"date": "20260318", "close": 1730.0}, {"date": "20260319", "close": 1680.0}, {"date": "20260320", "close": 1700.0}, {"date": "20260323", "close": 1625.0}, {"date": "20260324", "close": 1620.0}, {"date": "20260325", "close": 1620.0}, {"date": "20260326", "close": 1590.0}, {"date": "20260327", "close": 1585.0}, {"date": "20260330", "close": 1510.0}, {"date": "20260331", "close": 1490.0}, {"date": "20260401", "close": 1465.0}, {"date": "20260402", "close": 1465.0}, {"date": "20260407", "close": 1470.0}, {"date": "20260408", "close": 1580.0}, {"date": "20260409", "close": 1575.0}, {"date": "20260410", "close": 1575.0}, {"date": "20260413", "close": 1620.0}, {"date": "20260414", "close": 1720.0}, {"date": "20260415", "close": 1790.0}, {"date": "20260416", "close": 1895.0}, {"date": "20260417", "close": 1925.0}], "AIXA GY": [], "2368": [{"date": "20251103", "close": 493.0}, {"date": "20251104", "close": 483.0}, {"date": "20251105", "close": 464.5}, {"date": "20251106", "close": 478.5}, {"date": "20251107", "close": 464.5}, {"date": "20251110", "close": 482.0}, {"date": "20251111", "close": 498.5}, {"date": "20251112", "close": 548.0}, {"date": "20251113", "close": 567.0}, {"date": "20251114", "close": 544.0}, {"date": "20251117", "close": 537.0}, {"date": "20251118", "close": 507.0}, {"date": "20251119", "close": 522.0}, {"date": "20251120", "close": 574.0}, {"date": "20251121", "close": 550.0}, {"date": "20251124", "close": 540.0}, {"date": "20251125", "close": 594.0}, {"date": "20251126", "close": 610.0}, {"date": "20251127", "close": 627.0}, {"date": "20251128", "close": 633.0}, {"date": "20251201", "close": 622.0}, {"date": "20251202", "close": 600.0}, {"date": "20251203", "close": 589.0}, {"date": "20251204", "close": 582.0}, {"date": "20251205", "close": 596.0}, {"date": "20251208", "close": 588.0}, {"date": "20251209", "close": 596.0}, {"date": "20251210", "close": 616.0}, {"date": "20251211", "close": 603.0}, {"date": "20251212", "close": 618.0}, {"date": "20251215", "close": 603.0}, {"date": "20251216", "close": 594.0}, {"date": "20251217", "close": 586.0}, {"date": "20251218", "close": 589.0}, {"date": "20251219", "close": 608.0}, {"date": "20251222", "close": 650.0}, {"date": "20251223", "close": 651.0}, {"date": "20251224", "close": 668.0}, {"date": "20251226", "close": 697.0}, {"date": "20251229", "close": 697.0}, {"date": "20251230", "close": 692.0}, {"date": "20251231", "close": 687.0}, {"date": "20260102", "close": 643.0}, {"date": "20260105", "close": 634.0}, {"date": "20260106", "close": 662.0}, {"date": "20260107", "close": 643.0}, {"date": "20260108", "close": 632.0}, {"date": "20260109", "close": 637.0}, {"date": "20260112", "close": 666.0}, {"date": "20260113", "close": 655.0}, {"date": "20260114", "close": 678.0}, {"date": "20260115", "close": 668.0}, {"date": "20260116", "close": 677.0}, {"date": "20260119", "close": 624.0}, {"date": "20260120", "close": 630.0}, {"date": "20260121", "close": 596.0}, {"date": "20260122", "close": 626.0}, {"date": "20260123", "close": 646.0}, {"date": "20260126", "close": 666.0}, {"date": "20260127", "close": 686.0}, {"date": "20260128", "close": 720.0}, {"date": "20260129", "close": 692.0}, {"date": "20260130", "close": 701.0}, {"date": "20260202", "close": 706.0}, {"date": "20260203", "close": 755.0}, {"date": "20260204", "close": 797.0}, {"date": "20260205", "close": 760.0}, {"date": "20260206", "close": 745.0}, {"date": "20260209", "close": 797.0}, {"date": "20260210", "close": 846.0}, {"date": "20260211", "close": 829.0}, {"date": "20260223", "close": 818.0}, {"date": "20260224", "close": 833.0}, {"date": "20260225", "close": 845.0}, {"date": "20260226", "close": 826.0}, {"date": "20260302", "close": 787.0}, {"date": "20260303", "close": 766.0}, {"date": "20260304", "close": 709.0}, {"date": "20260305", "close": 736.0}, {"date": "20260306", "close": 792.0}, {"date": "20260309", "close": 761.0}, {"date": "20260310", "close": 817.0}, {"date": "20260311", "close": 898.0}, {"date": "20260312", "close": 911.0}, {"date": "20260313", "close": 935.0}, {"date": "20260316", "close": 909.0}, {"date": "20260317", "close": 917.0}, {"date": "20260318", "close": 917.0}, {"date": "20260319", "close": 1005.0}, {"date": "20260320", "close": 988.0}, {"date": "20260323", "close": 962.0}, {"date": "20260324", "close": 888.0}, {"date": "20260325", "close": 922.0}, {"date": "20260326", "close": 918.0}, {"date": "20260327", "close": 924.0}, {"date": "20260330", "close": 898.0}, {"date": "20260331", "close": 860.0}, {"date": "20260401", "close": 946.0}, {"date": "20260402", "close": 905.0}, {"date": "20260407", "close": 927.0}, {"date": "20260408", "close": 998.0}, {"date": "20260409", "close": 1095.0}, {"date": "20260410", "close": 1090.0}, {"date": "20260413", "close": 1055.0}, {"date": "20260414", "close": 1150.0}, {"date": "20260415", "close": 1165.0}, {"date": "20260416", "close": 1165.0}, {"date": "20260417", "close": 1175.0}], "2360": [{"date": "20251103", "close": 811.0}, {"date": "20251104", "close": 776.0}, {"date": "20251105", "close": 762.0}, {"date": "20251106", "close": 753.0}, {"date": "20251107", "close": 741.0}, {"date": "20251110", "close": 744.0}, {"date": "20251111", "close": 760.0}, {"date": "20251112", "close": 798.0}, {"date": "20251113", "close": 807.0}, {"date": "20251114", "close": 785.0}, {"date": "20251117", "close": 774.0}, {"date": "20251118", "close": 746.0}, {"date": "20251119", "close": 770.0}, {"date": "20251120", "close": 808.0}, {"date": "20251121", "close": 774.0}, {"date": "20251124", "close": 810.0}, {"date": "20251125", "close": 829.0}, {"date": "20251126", "close": 800.0}, {"date": "20251127", "close": 811.0}, {"date": "20251128", "close": 819.0}, {"date": "20251201", "close": 785.0}, {"date": "20251202", "close": 778.0}, {"date": "20251203", "close": 805.0}, {"date": "20251204", "close": 776.0}, {"date": "20251205", "close": 796.0}, {"date": "20251208", "close": 805.0}, {"date": "20251209", "close": 808.0}, {"date": "20251210", "close": 800.0}, {"date": "20251211", "close": 796.0}, {"date": "20251212", "close": 805.0}, {"date": "20251215", "close": 769.0}, {"date": "20251216", "close": 746.0}, {"date": "20251217", "close": 740.0}, {"date": "20251218", "close": 728.0}, {"date": "20251219", "close": 741.0}, {"date": "20251222", "close": 756.0}, {"date": "20251223", "close": 763.0}, {"date": "20251224", "close": 771.0}, {"date": "20251226", "close": 789.0}, {"date": "20251229", "close": 781.0}, {"date": "20251230", "close": 790.0}, {"date": "20251231", "close": 775.0}, {"date": "20260102", "close": 796.0}, {"date": "20260105", "close": 811.0}, {"date": "20260106", "close": 856.0}, {"date": "20260107", "close": 922.0}, {"date": "20260108", "close": 925.0}, {"date": "20260109", "close": 923.0}, {"date": "20260112", "close": 954.0}, {"date": "20260113", "close": 984.0}, {"date": "20260114", "close": 989.0}, {"date": "20260115", "close": 966.0}, {"date": "20260116", "close": 989.0}, {"date": "20260119", "close": 950.0}, {"date": "20260120", "close": 1030.0}, {"date": "20260121", "close": 995.0}, {"date": "20260122", "close": 1010.0}, {"date": "20260123", "close": 1025.0}, {"date": "20260126", "close": 1015.0}, {"date": "20260127", "close": 1035.0}, {"date": "20260128", "close": 1035.0}, {"date": "20260129", "close": 1015.0}, {"date": "20260130", "close": 980.0}, {"date": "20260202", "close": 971.0}, {"date": "20260203", "close": 1040.0}, {"date": "20260204", "close": 1030.0}, {"date": "20260205", "close": 974.0}, {"date": "20260206", "close": 967.0}, {"date": "20260209", "close": 1030.0}, {"date": "20260210", "close": 1040.0}, {"date": "20260211", "close": 1050.0}, {"date": "20260223", "close": 1155.0}, {"date": "20260224", "close": 1225.0}, {"date": "20260225", "close": 1255.0}, {"date": "20260226", "close": 1380.0}, {"date": "20260302", "close": 1515.0}, {"date": "20260303", "close": 1395.0}, {"date": "20260304", "close": 1340.0}, {"date": "20260305", "close": 1405.0}, {"date": "20260306", "close": 1375.0}, {"date": "20260309", "close": 1240.0}, {"date": "20260310", "close": 1360.0}, {"date": "20260311", "close": 1495.0}, {"date": "20260312", "close": 1495.0}, {"date": "20260313", "close": 1530.0}, {"date": "20260316", "close": 1450.0}, {"date": "20260317", "close": 1470.0}, {"date": "20260318", "close": 1565.0}, {"date": "20260319", "close": 1595.0}, {"date": "20260320", "close": 1585.0}, {"date": "20260323", "close": 1520.0}, {"date": "20260324", "close": 1480.0}, {"date": "20260325", "close": 1625.0}, {"date": "20260326", "close": 1640.0}, {"date": "20260327", "close": 1615.0}, {"date": "20260330", "close": 1625.0}, {"date": "20260331", "close": 1465.0}, {"date": "20260401", "close": 1610.0}, {"date": "20260402", "close": 1535.0}, {"date": "20260407", "close": 1570.0}, {"date": "20260408", "close": 1725.0}, {"date": "20260409", "close": 1840.0}, {"date": "20260410", "close": 1785.0}, {"date": "20260413", "close": 1880.0}, {"date": "20260414", "close": 1840.0}, {"date": "20260415", "close": 2020.0}, {"date": "20260416", "close": 2050.0}, {"date": "20260417", "close": 2255.0}], "7826 JP": [], "KLAC US": [], "3715": [{"date": "20251103", "close": 92.6}, {"date": "20251104", "close": 90.2}, {"date": "20251105", "close": 92.2}, {"date": "20251106", "close": 92.6}, {"date": "20251107", "close": 93.0}, {"date": "20251110", "close": 101.5}, {"date": "20251111", "close": 111.5}, {"date": "20251112", "close": 119.0}, {"date": "20251113", "close": 130.5}, {"date": "20251114", "close": 120.5}, {"date": "20251117", "close": 120.5}, {"date": "20251118", "close": 116.5}, {"date": "20251119", "close": 113.5}, {"date": "20251120", "close": 123.0}, {"date": "20251121", "close": 111.0}, {"date": "20251124", "close": 108.5}, {"date": "20251125", "close": 119.0}, {"date": "20251126", "close": 118.5}, {"date": "20251127", "close": 118.0}, {"date": "20251128", "close": 118.5}, {"date": "20251201", "close": 116.0}, {"date": "20251202", "close": 114.5}, {"date": "20251203", "close": 114.5}, {"date": "20251204", "close": 111.5}, {"date": "20251205", "close": 112.0}, {"date": "20251208", "close": 117.0}, {"date": "20251209", "close": 116.0}, {"date": "20251210", "close": 117.0}, {"date": "20251211", "close": 121.5}, {"date": "20251212", "close": 120.0}, {"date": "20251215", "close": 118.0}, {"date": "20251216", "close": 114.5}, {"date": "20251217", "close": 114.0}, {"date": "20251218", "close": 112.5}, {"date": "20251219", "close": 118.5}, {"date": "20251222", "close": 120.0}, {"date": "20251223", "close": 122.0}, {"date": "20251224", "close": 119.5}, {"date": "20251226", "close": 123.5}, {"date": "20251229", "close": 119.5}, {"date": "20251230", "close": 121.0}, {"date": "20251231", "close": 127.5}, {"date": "20260102", "close": 127.0}, {"date": "20260105", "close": 119.0}, {"date": "20260106", "close": 118.0}, {"date": "20260107", "close": 117.0}, {"date": "20260108", "close": 127.0}, {"date": "20260109", "close": 139.5}, {"date": "20260112", "close": 144.5}, {"date": "20260113", "close": 137.5}, {"date": "20260114", "close": 133.0}, {"date": "20260115", "close": 131.5}, {"date": "20260116", "close": 134.5}, {"date": "20260119", "close": 132.0}, {"date": "20260120", "close": 131.5}, {"date": "20260121", "close": 134.0}, {"date": "20260122", "close": 136.5}, {"date": "20260123", "close": 141.5}, {"date": "20260126", "close": 155.5}, {"date": "20260127", "close": 149.0}, {"date": "20260128", "close": 150.0}, {"date": "20260129", "close": 143.0}, {"date": "20260130", "close": 143.0}, {"date": "20260202", "close": 138.0}, {"date": "20260203", "close": 143.5}, {"date": "20260204", "close": 157.5}, {"date": "20260205", "close": 151.0}, {"date": "20260206", "close": 142.0}, {"date": "20260209", "close": 143.5}, {"date": "20260210", "close": 142.5}, {"date": "20260211", "close": 141.0}, {"date": "20260223", "close": 140.5}, {"date": "20260224", "close": 145.0}, {"date": "20260225", "close": 153.0}, {"date": "20260226", "close": 158.0}, {"date": "20260302", "close": 153.0}, {"date": "20260303", "close": 153.0}, {"date": "20260304", "close": 145.0}, {"date": "20260305", "close": 149.5}, {"date": "20260306", "close": 153.5}, {"date": "20260309", "close": 139.0}, {"date": "20260310", "close": 146.5}, {"date": "20260311", "close": 152.0}, {"date": "20260312", "close": 151.5}, {"date": "20260313", "close": 166.0}, {"date": "20260316", "close": 161.5}, {"date": "20260317", "close": 158.0}, {"date": "20260318", "close": 173.5}, {"date": "20260319", "close": 190.5}, {"date": "20260320", "close": 178.5}, {"date": "20260323", "close": 170.5}, {"date": "20260324", "close": 166.5}, {"date": "20260325", "close": 183.0}, {"date": "20260326", "close": 185.0}, {"date": "20260327", "close": 203.5}, {"date": "20260330", "close": 185.0}, {"date": "20260331", "close": 175.0}, {"date": "20260401", "close": 180.0}, {"date": "20260402", "close": 172.0}, {"date": "20260407", "close": 181.5}, {"date": "20260408", "close": 194.5}, {"date": "20260409", "close": 187.0}, {"date": "20260410", "close": 186.5}, {"date": "20260413", "close": 186.5}, {"date": "20260414", "close": 186.5}, {"date": "20260415", "close": 185.5}, {"date": "20260416", "close": 186.5}, {"date": "20260417", "close": 198.0}], "6525 JP": [], "SAF FP": [], "268A JP": [], "NBIS US": [], "LGN US": [], "CWR LN": [], "SOI FP": [], "OKLO US": [], "AXTI US": [], "LEU US": [], "6869 HK": [], "4971 JP": [], "VIAV US": [], "BKSY US": [], "KEYS US": [], "SOLS US": [], "6997 JP": [], "MP US": [], "C_CNH": [], "3711": [{"date": "20251103", "close": 246.0}, {"date": "20251104", "close": 239.0}, {"date": "20251105", "close": 235.0}, {"date": "20251106", "close": 234.0}, {"date": "20251107", "close": 228.5}, {"date": "20251110", "close": 228.5}, {"date": "20251111", "close": 228.0}, {"date": "20251112", "close": 227.0}, {"date": "20251113", "close": 231.5}, {"date": "20251114", "close": 222.5}, {"date": "20251117", "close": 220.0}, {"date": "20251118", "close": 215.0}, {"date": "20251119", "close": 209.5}, {"date": "20251120", "close": 222.5}, {"date": "20251121", "close": 209.0}, {"date": "20251124", "close": 210.5}, {"date": "20251125", "close": 212.0}, {"date": "20251126", "close": 217.5}, {"date": "20251127", "close": 230.5}, {"date": "20251128", "close": 229.5}, {"date": "20251201", "close": 224.5}, {"date": "20251202", "close": 228.5}, {"date": "20251203", "close": 229.0}, {"date": "20251204", "close": 228.0}, {"date": "20251205", "close": 231.0}, {"date": "20251208", "close": 237.5}, {"date": "20251209", "close": 240.0}, {"date": "20251210", "close": 244.5}, {"date": "20251211", "close": 244.5}, {"date": "20251212", "close": 243.5}, {"date": "20251215", "close": 234.0}, {"date": "20251216", "close": 229.0}, {"date": "20251217", "close": 228.5}, {"date": "20251218", "close": 222.0}, {"date": "20251219", "close": 229.5}, {"date": "20251222", "close": 232.0}, {"date": "20251223", "close": 234.5}, {"date": "20251224", "close": 234.5}, {"date": "20251226", "close": 240.5}, {"date": "20251229", "close": 251.0}, {"date": "20251230", "close": 249.0}, {"date": "20251231", "close": 250.5}, {"date": "20260102", "close": 258.0}, {"date": "20260105", "close": 263.5}, {"date": "20260106", "close": 271.5}, {"date": "20260107", "close": 275.0}, {"date": "20260108", "close": 273.5}, {"date": "20260109", "close": 272.0}, {"date": "20260112", "close": 283.0}, {"date": "20260113", "close": 289.5}, {"date": "20260114", "close": 294.5}, {"date": "20260115", "close": 298.5}, {"date": "20260116", "close": 303.5}, {"date": "20260119", "close": 299.0}, {"date": "20260120", "close": 296.0}, {"date": "20260121", "close": 291.0}, {"date": "20260122", "close": 298.0}, {"date": "20260123", "close": 307.5}, {"date": "20260126", "close": 312.0}, {"date": "20260127", "close": 306.5}, {"date": "20260128", "close": 314.0}, {"date": "20260129", "close": 310.0}, {"date": "20260130", "close": 297.0}, {"date": "20260202", "close": 292.0}, {"date": "20260203", "close": 302.0}, {"date": "20260204", "close": 302.5}, {"date": "20260205", "close": 284.0}, {"date": "20260206", "close": 304.5}, {"date": "20260209", "close": 327.0}, {"date": "20260210", "close": 344.0}, {"date": "20260211", "close": 354.5}, {"date": "20260223", "close": 349.0}, {"date": "20260224", "close": 381.5}, {"date": "20260225", "close": 389.0}, {"date": "20260226", "close": 387.5}, {"date": "20260302", "close": 370.5}, {"date": "20260303", "close": 359.5}, {"date": "20260304", "close": 327.5}, {"date": "20260305", "close": 353.5}, {"date": "20260306", "close": 342.0}, {"date": "20260309", "close": 320.0}, {"date": "20260310", "close": 335.5}, {"date": "20260311", "close": 345.5}, {"date": "20260312", "close": 335.0}, {"date": "20260313", "close": 341.5}, {"date": "20260316", "close": 337.5}, {"date": "20260317", "close": 342.0}, {"date": "20260318", "close": 357.5}, {"date": "20260319", "close": 347.0}, {"date": "20260320", "close": 344.0}, {"date": "20260323", "close": 329.5}, {"date": "20260324", "close": 332.5}, {"date": "20260325", "close": 352.0}, {"date": "20260326", "close": 359.0}, {"date": "20260327", "close": 353.5}, {"date": "20260330", "close": 353.5}, {"date": "20260331", "close": 328.5}, {"date": "20260401", "close": 361.0}, {"date": "20260402", "close": 361.0}, {"date": "20260407", "close": 352.0}, {"date": "20260408", "close": 383.0}, {"date": "20260409", "close": 392.0}, {"date": "20260410", "close": 393.0}, {"date": "20260413", "close": 417.5}, {"date": "20260414", "close": 424.0}, {"date": "20260415", "close": 446.5}, {"date": "20260416", "close": 450.5}, {"date": "20260417", "close": 442.0}], "SMHN GY": [], "M_USD": [], "RKLB US": []}, "source": "finmind_v4", "generated_at": "2026-04-20T14:10:37Z"}