{"as_of": "20260420", "first_date": "20260416", "codes": ["2330", "2383", "3037", "8299", "2308", "2345", "5274", "6223", "2408", "3017", "7769", "8046", "2368", "2360", "3653", "3189", "2454", "3665", "6442", "6515", "3711", "2059", "6510", "2382", "2327", "2449", "2313", "3036", "2317", "2603", "1590", "3231", "5347", "2337", "1519", "6274", "2881", "2404", "8210", "2344", "2882", "2891", "2885", "2890", "3044", "2645"], "prices": {"2330": [{"date": "20260416", "close": 2085.0}, {"date": "20260417", "close": 2030.0}, {"date": "20260420", "close": 2025.0}], "2383": [{"date": "20260416", "close": 3835.0}, {"date": "20260417", "close": 3800.0}, {"date": "20260420", "close": 3850.0}], "3037": [{"date": "20260416", "close": 645.0}, {"date": "20260417", "close": 643.0}, {"date": "20260420", "close": 678.0}], "8299": [{"date": "20260416", "close": 1585.0}, {"date": "20260417", "close": 1570.0}, {"date": "20260420", "close": 1635.0}], "2308": [{"date": "20260416", "close": 1845.0}, {"date": "20260417", "close": 1840.0}, {"date": "20260420", "close": 1900.0}], "2345": [{"date": "20260416", "close": 2035.0}, {"date": "20260417", "close": 2070.0}, {"date": "20260420", "close": 2005.0}], "5274": [{"date": "20260416", "close": 14480.0}, {"date": "20260417", "close": 13805.0}, {"date": "20260420", "close": 14425.0}], "6223": [{"date": "20260416", "close": 4915.0}, {"date": "20260417", "close": 5195.0}, {"date": "20260420", "close": 5135.0}], "2408": [{"date": "20260416", "close": 213.5}, {"date": "20260417", "close": 210.0}, {"date": "20260420", "close": 207.0}], "3017": [{"date": "20260416", "close": 2440.0}, {"date": "20260417", "close": 2400.0}, {"date": "20260420", "close": 2490.0}], "7769": [{"date": "20260416", "close": 4295.0}, {"date": "20260417", "close": 4500.0}, {"date": "20260420", "close": 4445.0}], "8046": [{"date": "20260416", "close": 721.0}, {"date": "20260417", "close": 724.0}, {"date": "20260420", "close": 796.0}], "2368": [{"date": "20260416", "close": 1165.0}, {"date": "20260417", "close": 1175.0}, {"date": "20260420", "close": 1210.0}], "2360": [{"date": "20260416", "close": 2050.0}, {"date": "20260417", "close": 2255.0}, {"date": "20260420", "close": 2050.0}], "3653": [{"date": "20260416", "close": 4380.0}, {"date": "20260417", "close": 4565.0}, {"date": "20260420", "close": 5020.0}], "3189": [{"date": "20260416", "close": 393.5}, {"date": "20260417", "close": 391.5}, {"date": "20260420", "close": 430.5}], "2454": [{"date": "20260416", "close": 1895.0}, {"date": "20260417", "close": 1925.0}, {"date": "20260420", "close": 1900.0}], "3665": [{"date": "20260416", "close": 2395.0}, {"date": "20260417", "close": 2365.0}, {"date": "20260420", "close": 2460.0}], "6442": [{"date": "20260416", "close": 2075.0}, {"date": "20260417", "close": 2155.0}, {"date": "20260420", "close": 2370.0}], "6515": [{"date": "20260416", "close": 9820.0}, {"date": "20260417", "close": 10305.0}, {"date": "20260420", "close": 10795.0}], "3711": [{"date": "20260416", "close": 450.5}, {"date": "20260417", "close": 442.0}, {"date": "20260420", "close": 461.5}], "2059": [{"date": "20260416", "close": 3445.0}, {"date": "20260417", "close": 3640.0}, {"date": "20260420", "close": 3745.0}], "6510": [{"date": "20260416", "close": 3660.0}, {"date": "20260417", "close": 3740.0}, {"date": "20260420", "close": 3810.0}], "2382": [{"date": "20260416", "close": 318.5}, {"date": "20260417", "close": 323.0}, {"date": "20260420", "close": 329.0}], "2327": [{"date": "20260416", "close": 325.0}, {"date": "20260417", "close": 316.5}, {"date": "20260420", "close": 319.5}], "2449": [{"date": "20260416", "close": 283.5}, {"date": "20260417", "close": 275.0}, {"date": "20260420", "close": 271.0}], "2313": [{"date": "20260416", "close": 260.0}, {"date": "20260417", "close": 261.5}, {"date": "20260420", "close": 250.5}], "3036": [{"date": "20260416", "close": 235.0}, {"date": "20260417", "close": 230.0}, {"date": "20260420", "close": 217.0}], "2317": [{"date": "20260416", "close": 207.0}, {"date": "20260417", "close": 206.0}, {"date": "20260420", "close": 207.5}], "2603": [{"date": "20260416", "close": 201.5}, {"date": "20260417", "close": 198.0}, {"date": "20260420", "close": 197.0}], "1590": [{"date": "20260416", "close": 1225.0}, {"date": "20260417", "close": 1255.0}, {"date": "20260420", "close": 1275.0}], "3231": [{"date": "20260416", "close": 134.0}, {"date": "20260417", "close": 136.5}, {"date": "20260420", "close": 140.5}], "5347": [{"date": "20260416", "close": 132.5}, {"date": "20260417", "close": 132.0}, {"date": "20260420", "close": 139.0}], "2337": [{"date": "20260416", "close": 139.0}, {"date": "20260417", "close": 131.0}, {"date": "20260420", "close": 120.5}], "1519": [{"date": "20260416", "close": 872.0}, {"date": "20260417", "close": 872.0}, {"date": "20260420", "close": 891.0}], "6274": [{"date": "20260416", "close": 960.0}, {"date": "20260417", "close": 946.0}, {"date": "20260420", "close": 950.0}], "2881": [{"date": "20260416", "close": 87.9}, {"date": "20260417", "close": 88.0}, {"date": "20260420", "close": 87.2}], "2404": [{"date": "20260416", "close": 935.0}, {"date": "20260417", "close": 1025.0}, {"date": "20260420", "close": 1025.0}], "8210": [{"date": "20260416", "close": 1020.0}, {"date": "20260417", "close": 1020.0}, {"date": "20260420", "close": 1020.0}], "2344": [{"date": "20260416", "close": 89.6}, {"date": "20260417", "close": 87.8}, {"date": "20260420", "close": 85.7}], "2882": [{"date": "20260416", "close": 74.2}, {"date": "20260417", "close": 75.0}, {"date": "20260420", "close": 74.6}], "2891": [{"date": "20260416", "close": 53.4}, {"date": "20260417", "close": 53.1}, {"date": "20260420", "close": 53.1}], "2885": [{"date": "20260416", "close": 50.7}, {"date": "20260417", "close": 50.2}, {"date": "20260420", "close": 51.2}], "2890": [{"date": "20260416", "close": 33.3}, {"date": "20260417", "close": 32.7}, {"date": "20260420", "close": 32.2}], "3044": [{"date": "20260416", "close": 410.5}, {"date": "20260417", "close": 411.5}, {"date": "20260420", "close": 413.5}], "2645": [{"date": "20260416", "close": 157.0}, {"date": "20260417", "close": 160.5}, {"date": "20260420", "close": 166.0}]}, "source": "finmind_v4", "generated_at": "2026-04-20T12:50:49Z"}